shinkansen/__init__.py
shinkansen/common.py
shinkansen/jws.py
shinkansen/payins.py
shinkansen/payouts.py
shinkansen/responses.py
python_shinkansen-0.8.3.dist-info/METADATA
python_shinkansen-0.8.3.dist-info/WHEEL
python_shinkansen-0.8.3.dist-info/RECORD
