Metadata-Version: 2.4
Name: python-shinkansen
Version: 0.8.3
Summary: Python helpers for Shinkansen
Author: Leonardo Soto M.
Author-email: leo.soto@gmail.com
Requires-Python: >=3.10,<4.0
Classifier: Programming Language :: Python :: 3
Classifier: Programming Language :: Python :: 3.10
Classifier: Programming Language :: Python :: 3.11
Classifier: Programming Language :: Python :: 3.12
Classifier: Programming Language :: Python :: 3.13
Classifier: Programming Language :: Python :: 3.14
Requires-Dist: cryptography (>=44,<47)
Requires-Dist: jwcrypto (>=1.4.0,<2.0.0)
Requires-Dist: requests (>=2.28.1,<3.0.0)
Requires-Dist: setuptools (>=70.0.0,<71.0.0)
